setup.py
halofun/__init__.py
halofun.egg-info/PKG-INFO
halofun.egg-info/SOURCES.txt
halofun.egg-info/dependency_links.txt
halofun.egg-info/not-zip-safe
halofun.egg-info/top_level.txt