Metadata-Version: 1.0
Name: halofun
Version: 0.1
Summary: The funniest joke in the world
Home-page: http://github.com/vipin08/halofun
Author: Flying Circus
Author-email: vpnkumar.kumar1@gmail.com
License: MIT
Platform: UNKNOWN
